[{"layout":"PageError","comments":true,"title":null,"__filename":"404.md","__url":"/404/"},{"layout":"Posts","comments":true,"title":"Les articles","collection":"index","__filename":"fr/articles/index.md","__url":"/fr/articles/"},{"layout":"Post","comments":true,"date":"2015-05-21","title":"Qu'est-ce que l'intégration continue ?","tags":["ci","tests"],"authors":["MoOx"],"header":{"credit":"https://www.flickr.com/photos/zunami/3780218641/"},"__filename":"fr/articles/ci/index.md","__url":"/fr/articles/ci/"},{"layout":"Post","comments":true,"date":"2015-05-25","title":"Introduction au déploiement continu","tags":["ci","tests"],"authors":["MoOx"],"header":{"linearGradient":"160deg, rgb(204, 51, 51), rgba(204, 51, 51, .6)","credit":"https://www.flickr.com/photos/luciano_meirelles/3461046001/"},"__filename":"fr/articles/ci/deploiement-continu/index.md","__url":"/fr/articles/ci/deploiement-continu/"},{"layout":"Post","comments":true,"date":"2014-02-20","title":"La puissance de dnsmasq","tags":["dnsmasq","macosx","test","dns","serveur"],"authors":["kud"],"__filename":"fr/articles/dnsmasq/index.md","__url":"/fr/articles/dnsmasq/"},{"layout":"Post","comments":true,"date":"2015-06-11","title":"Introduction à Docker","tags":["docker"],"authors":["Uhsac"],"header":{"credit":"https://www.flickr.com/photos/68359921@N08/16097336663/"},"__filename":"fr/articles/docker/index.md","__url":"/fr/articles/docker/"},{"layout":"Post","comments":true,"date":"2015-07-02","title":"Les Dockerfiles","tags":["docker"],"authors":["Uhsac"],"header":{"credit":"https://www.flickr.com/photos/tristantaussac/15145365916/"},"__filename":"fr/articles/docker/dockerfile/index.md","__url":"/fr/articles/docker/dockerfile/"},{"layout":"Post","comments":true,"date":"2015-11-17","title":"Un favicon vite fait bien fait","tags":["favicon","gulp","grunt"],"authors":["phbernard"],"header":{"image":"index.jpg","linearGradient":"160deg, rgb(91, 91, 91), rgba(51, 51, 51, 0.6)"},"__filename":"fr/articles/favicon/index.md","__url":"/fr/articles/favicon/"},{"layout":"Post","comments":true,"date":"2013-11-06","title":"Versionner avec Git","tags":["git"],"authors":["madx"],"__filename":"fr/articles/git/index.md","__url":"/fr/articles/git/"},{"layout":"Post","comments":true,"date":"2014-02-27","title":"Git, boutez les bugs, domptez votre historique!","tags":["git"],"authors":["Erwyn"],"__filename":"fr/articles/git/log-bisect-rebase-reflog/index.md","__url":"/fr/articles/git/log-bisect-rebase-reflog/"},{"layout":"Post","comments":true,"date":"2013-11-07","title":"HTML ? Hache-Thé-Aime-Elle vous dites ?","tags":["html"],"authors":["MoOx"],"__filename":"fr/articles/html/index.md","__url":"/fr/articles/html/"},{"layout":"Post","comments":true,"date":"2013-12-26","title":"Responsive webdesign et structure du DOM","tags":["responsive","html","javascript"],"authors":["neemzy"],"__filename":"fr/articles/html/responsive-dom/index.md","__url":"/fr/articles/html/responsive-dom/"},{"layout":"Post","comments":true,"date":"2014-11-03","title":"Laissez-vous pousser la barbe, apprenez à écrire des Makefiles","tags":["shell","makefile"],"authors":["madx"],"__filename":"fr/articles/make/index.md","__url":"/fr/articles/make/"},{"layout":"Post","comments":true,"date":"2015-06-16","title":"SemVer, c'est quoi ?","tags":["semver"],"authors":["kud"],"header":{"linearGradient":"rgba(0,0,0, 0.6), rgba(0,0,0, 0.5)","credit":"https://www.flickr.com/photos/stevensnodgrass/5480863464/"},"__filename":"fr/articles/semver/index.md","__url":"/fr/articles/semver/"},{"layout":"Post","comments":true,"date":"2013-11-08","title":"Vagrant, enlarge your VM","tags":["virtualbox","tools","vagrant"],"authors":["lionelB"],"__filename":"fr/articles/vagrant/index.md","__url":"/fr/articles/vagrant/"},{"layout":"Post","comments":true,"date":"2015-03-03","title":"Il démarre Vim par erreur, ce qui se passe ensuite est tout simplement bluffant","tags":["éditeur","vim"],"authors":["MoOx"],"__filename":"fr/articles/vim/index.md","__url":"/fr/articles/vim/"},{"layout":"Post","comments":true,"date":"2014-10-21","title":"À la conquête des bugs","tags":["bug","webcompat","monoculture"],"authors":["magsout"],"__filename":"fr/articles/webcompat/index.md","__url":"/fr/articles/webcompat/"},{"layout":"Post","comments":true,"title":"C'est quoi Putain de code ?","__filename":"fr/c-est-quoi-putaindecode/index.md","__url":"/fr/c-est-quoi-putaindecode/"},{"layout":"Post","comments":true,"date":"2013-11-05","title":"Comment contribuer ?","tags":["putaindecode","contribuer"],"authors":["Nyalab"],"__filename":"fr/contribuer/index.md","__url":"/fr/contribuer/"},{"layout":"Homepage","comments":true,"title":"Putain de code !","__filename":"fr/index.md","__url":"/fr/"},{"layout":"Homepage","comments":true,"title":"Putain de code !","__filename":"index.md","__url":"//"},{"layout":"Post","comments":true,"date":"2015-03-12","title":"HATEOAS, le Graal des développeurs d'API","tags":["api","rest"],"authors":["awillemant"],"__filename":"fr/articles/api/hateoas/index.md","__url":"/fr/articles/api/hateoas/"},{"layout":"Post","comments":true,"date":"2014-02-25","title":"Comment en finir avec les préfixes CSS","tags":["css","préfixe","pré-processeur","post-processeur"],"authors":["MoOx"],"__filename":"fr/articles/css/autoprefixer/index.md","__url":"/fr/articles/css/autoprefixer/"},{"layout":"Post","comments":true,"date":"2014-03-04","title":"Mise en place d’autoprefixer","tags":["css","préfixe"],"authors":["MoOx"],"__filename":"fr/articles/css/autoprefixer/mise-en-place/index.md","__url":"/fr/articles/css/autoprefixer/mise-en-place/"},{"layout":"Post","comments":true,"date":"2014-05-05","title":"Petite définition de BEM","tags":["css","html","méthologie","convention"],"authors":["kud"],"__filename":"fr/articles/css/bem/index.md","__url":"/fr/articles/css/bem/"},{"layout":"Post","comments":true,"date":"2015-03-10","title":"Du CSS évolutif","tags":["css","bem"],"authors":["magsout"],"__filename":"fr/articles/css/bem/maintenance-evolutivite/index.md","__url":"/fr/articles/css/bem/maintenance-evolutivite/"},{"layout":"Post","comments":true,"date":"2014-09-23","title":"Le guide complet pour centrer en css","tags":["css"],"authors":["Nyalab"],"__filename":"fr/articles/css/centrer/index.md","__url":"/fr/articles/css/centrer/"},{"layout":"Post","comments":true,"date":"2014-03-11","title":"Le point sur les pré-processeurs CSS","tags":["css","pré-processeur","post-processeur"],"authors":["MoOx"],"__filename":"fr/articles/css/preprocesseurs/index.md","__url":"/fr/articles/css/preprocesseurs/"},{"layout":"Post","comments":true,"date":"2014-05-20","title":"Faire son préprocesseur CSS à la carte","tags":["css","preprocesseur","postprocesseur"],"authors":["MoOx"],"__filename":"fr/articles/css/preprocesseurs/a-la-carte/index.md","__url":"/fr/articles/css/preprocesseurs/a-la-carte/"},{"layout":"Post","comments":true,"date":"2015-06-02","title":"Introduction à cssnext","tags":["css","postcss"],"authors":["Macxim"],"header":{"credit":"https://www.flickr.com/photos/frinky/620935482"},"__filename":"fr/articles/css/preprocesseurs/cssnext/index.md","__url":"/fr/articles/css/preprocesseurs/cssnext/"},{"layout":"Post","comments":true,"date":"2014-04-08","title":"Les post-processeurs CSS","tags":["css","pré-processeur","post-processeur"],"authors":["MoOx"],"__filename":"fr/articles/css/preprocesseurs/post-processeurs/index.md","__url":"/fr/articles/css/preprocesseurs/post-processeurs/"},{"layout":"Post","comments":true,"date":"2014-06-13","title":"Un point sur les grilles CSS en inline-block","tags":["css","inline-block","grid"],"authors":["lionelB"],"__filename":"fr/articles/css/grilles/inline-block/index.md","__url":"/fr/articles/css/grilles/inline-block/"},{"layout":"Post","comments":true,"date":"2015-05-19","title":"Comment déboguer facilement du web y compris sur tablettes et téléphones","tags":["debug","frontend"],"authors":["kud"],"header":{"credit":"https://www.flickr.com/photos/adactio/6153558098"},"__filename":"fr/articles/devtools/deboguer-tablettes-telephones/index.md","__url":"/fr/articles/devtools/deboguer-tablettes-telephones/"},{"layout":"Post","comments":true,"date":"2014-10-30","title":"L'auto-entrepreneuriat : retour d'expériences","tags":["auto-entrepreneur","administratif","entreprendre"],"authors":["kud","MoOx"],"header":{"light":true,"linearGradient":"160deg, rgb(250, 250, 250), rgba(214, 194, 162, 0.6)","credit":"http://freebiesxpress.com/gallery/macbook-air-table-direct-stock-photo/"},"__filename":"fr/articles/entreprendre/auto-entrepreneuriat-retour-experiences/index.md","__url":"/fr/articles/entreprendre/auto-entrepreneuriat-retour-experiences/"},{"layout":"Post","comments":true,"date":"2013-12-05","title":"ExternalInterface.call() de Flash (et Backbone), toute une histoire","tags":["javascript","backbone","flash"],"authors":["kud"],"__filename":"fr/articles/flash/bug-externalinterface-call-backbone/index.md","__url":"/fr/articles/flash/bug-externalinterface-call-backbone/"},{"layout":"Post","comments":true,"date":"2014-05-15","title":"Se mettre au frontend en 2014, par où commencer ?","tags":["frontend","css","javascript","worflow","interview"],"authors":["kud"],"__filename":"fr/articles/frontend/2014-se-mettre-au-frontend/index.md","__url":"/fr/articles/frontend/2014-se-mettre-au-frontend/"},{"layout":"Post","comments":true,"date":"2014-12-15","title":"JavaScript modulaire pour le front-end : les bases","tags":["javascript","amd","commonjs","browserify","npm","requirejs","bower"],"authors":["syvuilliot"],"__filename":"fr/articles/frontend/2015-etat-lieux-javascript-modulaire/index.md","__url":"/fr/articles/frontend/2015-etat-lieux-javascript-modulaire/"},{"layout":"Post","comments":true,"date":"2015-06-09","title":"Les webhooks GitHub","tags":["github","webhooks"],"authors":["magsout"],"header":{"credit":"https://www.flickr.com/photos/haru__q/14396323454/"},"__filename":"fr/articles/github/webhooks/index.md","__url":"/fr/articles/github/webhooks/"},{"layout":"Post","comments":true,"date":"2015-07-31","title":"Créer un site web gratuitement avec GitHub Pages","tags":["github","html"],"authors":["revolunet"],"header":{"credit":"https://www.flickr.com/photos/expressmonorail/","linearGradient":"160deg, rgb(26, 37, 85), rgba(51, 98, 204, 0.6)"},"__filename":"fr/articles/github/pages/site-web-gratuit/index.md","__url":"/fr/articles/github/pages/site-web-gratuit/"},{"layout":"Post","comments":true,"date":"2013-11-11","title":"Structurer son projet avec Revel et Mgo","tags":["golang","mongo","revel","mgo"],"authors":["OwlyCode"],"__filename":"fr/articles/go/structure-revel-mgo/index.md","__url":"/fr/articles/go/structure-revel-mgo/"},{"layout":"Post","comments":true,"date":"2014-05-13","title":"Array.reduce par l'exemple","tags":["javascript","array"],"authors":["lionelB"],"__filename":"fr/articles/js/array-reduce/index.md","__url":"/fr/articles/js/array-reduce/"},{"layout":"Post","comments":true,"date":"2014-01-15","title":"BROWSERIFY ALL THE THINGS","tags":["javascript","amd","commonjs","browserify"],"authors":["MoOx"],"__filename":"fr/articles/js/browserify/index.md","__url":"/fr/articles/js/browserify/"},{"layout":"Post","comments":true,"date":"2013-12-06","title":"Comment se passer de libraries/frameworks JavaScript","tags":["javascript","frameworks","libraries"],"authors":["bloodyowl"],"__filename":"fr/articles/js/comment-se-passer-de-libraries-frameworks-javascript/index.md","__url":"/fr/articles/js/comment-se-passer-de-libraries-frameworks-javascript/"},{"layout":"Post","comments":true,"date":"2013-12-05","title":"De jQuery à Vanilla JS","tags":["javascript","jquery","vanillajs"],"authors":["kud"],"__filename":"fr/articles/js/de-jquery-a-vanillajs/index.md","__url":"/fr/articles/js/de-jquery-a-vanillajs/"},{"layout":"Post","comments":true,"date":"2014-10-20","title":"Débuter avec Ember","tags":["ember","javascript","frameworks"],"authors":["bmeurant"],"__filename":"fr/articles/js/ember/index.md","__url":"/fr/articles/js/ember/"},{"layout":"Post","comments":true,"date":"2014-10-27","title":"Flux, qu'est-ce que c'est ?","tags":["javascript","reactjs","flux"],"authors":["bloodyowl"],"__filename":"fr/articles/js/flux/index.md","__url":"/fr/articles/js/flux/"},{"layout":"Post","comments":true,"date":"2015-05-01","title":"Implémenter Flux","tags":["javascript","reactjs","flux"],"authors":["bloodyowl"],"__filename":"fr/articles/js/flux/implementer/index.md","__url":"/fr/articles/js/flux/implementer/"},{"layout":"Post","comments":true,"date":"2013-11-16","title":"Premiers pas avec Grunt","tags":["javascript","tools","grunt"],"authors":["kud"],"__filename":"fr/articles/js/grunt/index.md","__url":"/fr/articles/js/grunt/"},{"layout":"Post","comments":true,"date":"2014-04-29","title":"Introduction à Gulp","tags":["javascript","tools","gulp"],"authors":["MoOx"],"__filename":"fr/articles/js/gulp/index.md","__url":"/fr/articles/js/gulp/"},{"layout":"Post","comments":true,"date":"2014-05-14","title":"Créez vos iconfonts avec gulp-iconfont","tags":["gulp","nodejs","frontend","svg","fonts","glyphicons"],"authors":["kud"],"__filename":"fr/articles/js/gulp/icon-fonts/index.md","__url":"/fr/articles/js/gulp/icon-fonts/"},{"layout":"Post","comments":true,"date":"2014-06-04","title":"Introduction à ReactJS","tags":["javascript","reactjs"],"authors":["bloodyowl"],"__filename":"fr/articles/js/react/index.md","__url":"/fr/articles/js/react/"},{"layout":"Post","comments":true,"date":"2015-02-23","title":"Quelques retours sur React et le rendu serveur","tags":["javascript","react"],"authors":["lionelB"],"__filename":"fr/articles/js/react/cote-serveur/index.md","__url":"/fr/articles/js/react/cote-serveur/"},{"layout":"Post","comments":true,"date":"2015-05-07","title":"Utiliser React en moteur de templates","tags":["javascript","react"],"authors":["MoOx"],"__filename":"fr/articles/js/react/utiliser-en-moteur-de-templates/index.md","__url":"/fr/articles/js/react/utiliser-en-moteur-de-templates/"},{"layout":"Post","comments":true,"date":"2015-07-20","title":"Webpack","tags":["javascript","task-runner"],"authors":["MoOx"],"header":{"credit":"http://webpack.github.io/","linearGradient":"160deg, rgb(204, 51, 51), rgba(204, 51, 51, .6)"},"__filename":"fr/articles/js/webpack/index.md","__url":"/fr/articles/js/webpack/"},{"layout":"Post","comments":true,"date":"2015-07-21","title":"Premier exemple d'utilisation de Webpack","tags":["javascript","task-runner"],"authors":["MoOx"],"header":{"image":"../index.jpg","credit":"http://webpack.github.io/","linearGradient":"160deg, rgb(204, 51, 51), rgba(204, 51, 51, .6)"},"__filename":"fr/articles/js/webpack/premier-exemple/index.md","__url":"/fr/articles/js/webpack/premier-exemple/"},{"layout":"Post","comments":true,"date":"2014-10-27","title":"Première application Ember","tags":["ember","javascript","frameworks"],"authors":["bmeurant"],"__filename":"fr/articles/js/ember/premiere-app/1/index.md","__url":"/fr/articles/js/ember/premiere-app/1/"},{"layout":"Post","comments":true,"date":"2014-12-09","title":"Première application Ember. Suite et fin.","tags":["ember","javascript","frameworks"],"authors":["bmeurant"],"__filename":"fr/articles/js/ember/premiere-app/2/index.md","__url":"/fr/articles/js/ember/premiere-app/2/"},{"layout":"Post","comments":true,"date":"2014-05-01","title":"Introduction au testing js front","tags":["javascript","tape","unit-test","browserify"],"authors":["bloodyowl"],"__filename":"fr/articles/js/tests/frontend/index.md","__url":"/fr/articles/js/tests/frontend/"},{"layout":"Post","comments":true,"date":"2014-05-06","title":"NPM comme package manager pour le front-end","tags":["npm","package manager","javascript","css"],"authors":["kewah"],"__filename":"fr/articles/npm/frontend/index.md","__url":"/fr/articles/npm/frontend/"},{"layout":"Post","comments":true,"date":"2014-05-12","title":"napa ou comment télécharger un package qui napa de package.json","tags":["npm","javascript","nodejs"],"authors":["kud"],"__filename":"fr/articles/npm/napa/index.md","__url":"/fr/articles/npm/napa/"},{"layout":"Post","comments":true,"date":"2015-05-12","title":"Les utilitaires en ligne de commande","tags":["cli","npm","iojs/nodejs"],"authors":["magsout"],"__filename":"fr/articles/npm/utilitaire-cli/index.md","__url":"/fr/articles/npm/utilitaire-cli/"},{"layout":"Post","comments":true,"date":"2014-05-12","title":"npm: choisir la bonne version de ses dépendances","tags":["npm","javascript","nodejs"],"authors":["kud"],"__filename":"fr/articles/npm/versions-dependances/index.md","__url":"/fr/articles/npm/versions-dependances/"},{"layout":"Post","comments":true,"date":"2014-11-05","title":"L'injection de dépendances en PHP","tags":["php","php-di"],"authors":["neemzy"],"__filename":"fr/articles/php/injection-dependances/index.md","__url":"/fr/articles/php/injection-dependances/"},{"layout":"Post","comments":true,"date":"2014-10-14","title":"Dépendances et premier projet en Ruby","tags":["backend","ruby"],"authors":["rhannequin"],"__filename":"fr/articles/ruby/bundler/index.md","__url":"/fr/articles/ruby/bundler/"},{"layout":"Post","comments":true,"date":"2014-05-07","title":"Premiers pas avec Ruby","tags":["ruby"],"authors":["rhannequin"],"__filename":"fr/articles/ruby/premiers-pas/index.md","__url":"/fr/articles/ruby/premiers-pas/"},{"layout":"Post","comments":true,"date":"2014-07-16","title":"Maîtriser les redirections shell","tags":["shell"],"authors":["madx"],"__filename":"fr/articles/shell/redirections/index.md","__url":"/fr/articles/shell/redirections/"},{"layout":"Post","comments":true,"date":"2014-02-20","title":"Sublime Text en tant qu'éditeur Markdown","tags":["sublime-text","markdown"],"authors":["kud"],"__filename":"fr/articles/sublime-text/markdown/index.md","__url":"/fr/articles/sublime-text/markdown/"},{"layout":"Post","comments":true,"date":"2014-02-26","title":"Twitter comme lecteur de flux","tags":["twitter","rss","atom"],"authors":["kud"],"__filename":"fr/articles/twitter/comme-lecteur-de-flux/index.md","__url":"/fr/articles/twitter/comme-lecteur-de-flux/"},{"layout":"Post","comments":true,"date":"2014-10-15","title":"Comment essayer de coder comme un chef sous Windows","tags":["windows","outils","dev"],"authors":["kud"],"header":{"credit":"http://www.customity.com/content/wallpaper/windows-key-wallpaper"},"__filename":"fr/articles/windows/comment-coder-sous-windows/index.md","__url":"/fr/articles/windows/comment-coder-sous-windows/"},{"layout":"Post","comments":true,"date":"2015-10-20","title":"Gérer son thème WordPress avec Webpack","tags":["wordpress","webpack","javascript","task-runner"],"authors":["MoOx"],"header":{"credit":"https://www.flickr.com/photos/4everyoung/2505890793/","linearGradient":"160deg, rgb(204, 51, 51), rgba(204, 51, 51, .6)"},"__filename":"fr/articles/wordpress/webpack/index.md","__url":"/fr/articles/wordpress/webpack/"},{"layout":"Post","comments":true,"date":"2013-12-26","title":"Responsive webdesign and DOM structure","tags":["responsive","html","javascript"],"authors":["neemzy"],"__filename":"en/articles/html/responsive-dom/index.md","__url":"/en/articles/html/responsive-dom/"},{"layout":"Post","comments":true,"date":"2014-06-04","title":"Introduction to ReactJS","tags":["javascript","reactjs"],"authors":["bloodyowl"],"translators":["skinnyfoetusboy"],"__filename":"en/articles/js/react/index.md","__url":"/en/articles/js/react/"},{"layout":"Post","comments":true,"date":"2015-06-02","title":"Introduction to cssnext","tags":["css","postcss"],"authors":["Macxim"],"header":{"credit":"https://www.flickr.com/photos/frinky/620935482"},"__filename":"en/articles/css/preprocessors/cssnext/index.md","__url":"/en/articles/css/preprocessors/cssnext/"},{"layout":"Post","comments":true,"date":"2014-05-05","title":"Table ronde #3 - Les bonnes pratiques et organisation CSS/HTML","tags":["table-ronde","css","html"],"authors":["kud"],"__filename":"fr/evenements/2014/05/table-ronde-3/index.md","__url":"/fr/evenements/2014/05/table-ronde-3/"}]